reaction_local/__init__.py
reaction_local/constants.py
reaction_local/reaction.py
reaction_local/reaction_type.py
reaction_local-0.0.18.dist-info/METADATA
reaction_local-0.0.18.dist-info/WHEEL
reaction_local-0.0.18.dist-info/top_level.txt
reaction_local-0.0.18.dist-info/RECORD
