Metadata-Version: 2.1
Name: reaction-local
Version: 0.0.18
Summary: PyPI Package for Circles reaction-local-python-package Local Python
Home-page: https://github.com/circles-zone/reaction-local-python-package
Author: Circles
Author-email: info@circles.ai
Classifier: Programming Language :: Python :: 3
Classifier: License :: Other/Proprietary License
Classifier: Operating System :: OS Independent
Requires-Dist: database-mysql-local
Requires-Dist: logger-local
Requires-Dist: language-remote
